retry_async/__init__.py
retry_async/api.py
retry_async-0.1.4.dist-info/METADATA
retry_async-0.1.4.dist-info/WHEEL
retry_async-0.1.4.dist-info/RECORD
