Metadata-Version: 2.1
Name: retry-async
Version: 0.1.4
Summary: 
Author: Jeremy Berman
Author-email: jerber@sas.upenn.edu
Requires-Python: >=3.10,<4.0
Classifier: Programming Language :: Python :: 3
Classifier: Programming Language :: Python :: 3.10
Classifier: Programming Language :: Python :: 3.11
Requires-Dist: decorator (>=5.1.1,<6.0.0)
